pianosdk/__init__.py
pianosdk/access_token.py
pianosdk/api_response.py
pianosdk/base_api.py
pianosdk/configuration.py
pianosdk/constants.py
pianosdk/exceptions.py
pianosdk/piano_client.py
pianosdk/utils.py
pianosdk/webhook_events.py
pianosdk/anon/__init__.py
pianosdk/anon/api/__init__.py
pianosdk/anon/api/access_api.py
pianosdk/anon/api/access_token_api.py
pianosdk/anon/api/anon_assets_api.py
pianosdk/anon/api/anon_country_list_api.py
pianosdk/anon/api/anon_error_api.py
pianosdk/anon/api/anon_mobile_sdk_id_deployment_api.py
pianosdk/anon/api/anon_user_api.py
pianosdk/anon/api/anon_user_disable_api.py
pianosdk/anon/api/conversion_api.py
pianosdk/anon/api/conversion_external_api.py
pianosdk/anon/api/conversion_registration_api.py
pianosdk/anon/api/email_confirmation_api.py
pianosdk/anon/api/exposure_api.py
pianosdk/anon/api/oauth_api.py
pianosdk/anon/api/subscription_api.py
pianosdk/anon/api/swg_sync_api.py
pianosdk/anon/models/__init__.py
pianosdk/anon/models/access.py
pianosdk/anon/models/access_dto.py
pianosdk/anon/models/access_token_list.py
pianosdk/anon/models/billing_plan_translation_request.py
pianosdk/anon/models/check_subscription_response.py
pianosdk/anon/models/client_configurations_dto.py
pianosdk/anon/models/consent_model.py
pianosdk/anon/models/country.py
pianosdk/anon/models/currency.py
pianosdk/anon/models/datatrans_apple_pay_config.py
pianosdk/anon/models/external_css.py
pianosdk/anon/models/key_source.py
pianosdk/anon/models/light_offer_template_version.py
pianosdk/anon/models/linked_term_checkout_track_params.py
pianosdk/anon/models/linked_term_event_page_view_content.py
pianosdk/anon/models/linked_term_event_session.py
pianosdk/anon/models/linked_term_event_session_offer.py
pianosdk/anon/models/linked_term_page_view_content_params.py
pianosdk/anon/models/linked_term_session_params.py
pianosdk/anon/models/locale_model.py
pianosdk/anon/models/o_auth_token.py
pianosdk/anon/models/passwordless_purchase_check_result.py
pianosdk-16.675.0.dist-info/METADATA
pianosdk-16.675.0.dist-info/WHEEL
pianosdk-16.675.0.dist-info/top_level.txt
pianosdk-16.675.0.dist-info/RECORD
